Metadata-Version: 1.2
Name: tuningdeap
Version: 0.0.5
Summary: A package to tune Machine Learning hyperparameters with config files
Home-page: https://github.com/orionw/tuningDEAP
Author: Brandon Schoenfeld and Orion Weller
Author-email: orionw@byu.edu
License: MIT
Download-URL: https://github.com/orionw/tuningDEAP/archive/v0.0.5.tar.gz
Keywords: tuning machinelearning genetic hyperparameters
Platform: UNKNOWN
Classifier: Programming Language :: Python :: 3.5
Requires-Python: ~=3.5
